revml/__init__.py
revml/bytecode.py
revml/contract/__init__.py
revml/contract/layers.py
revml/contract/model.py
revml/contract/pipeline.py
revml/decontract/__init__.py
revml-0.6.15.dist-info/METADATA
revml-0.6.15.dist-info/WHEEL
revml-0.6.15.dist-info/RECORD
