Metadata-Version: 2.3
Name: revml
Version: 0.6.15
Summary: EVM (de)compiler using NN.
Author: apehex
Author-email: apehex@protonmail.com
Requires-Python: >=3.10,<3.13
Classifier: Programming Language :: Python :: 3
Classifier: Programming Language :: Python :: 3.10
Classifier: Programming Language :: Python :: 3.11
Classifier: Programming Language :: Python :: 3.12
Requires-Dist: mlable (>=0.20)
Requires-Dist: tensorflow (>=2.16,<2.20)
